[
  {
    "model": "registration.bcgreenhousegasid",
    "fields": {
      "id": "23219990005",
      "issued_at": "2023-10-13T15:27:00.000Z",
      "comments": "For Operation 1"
    }
  },
  {
    "model": "registration.bcgreenhousegasid",
    "fields": {
      "id": "23219990004",
      "issued_at": "2023-10-13T15:27:00.000Z",
      "comments": "For Operation 2"
    }
  },
  {
    "model": "registration.bcgreenhousegasid",
    "fields": {
      "id": "23219990003",
      "issued_at": "2023-10-13T15:27:00.000Z",
      "comments": "For Operation 3"
    }
  },
  {
    "model": "registration.bcgreenhousegasid",
    "fields": {
      "id": "23219990002",
      "issued_at": "2023-10-13T15:27:00.000Z",
      "comments": "For Operation 4"
    }
  },
  {
    "model": "registration.bcgreenhousegasid",
    "fields": {
      "id": "23219990001",
      "issued_at": "2023-10-13T15:27:00.000Z",
      "comments": "For Operation 5"
    }
  },
  {
    "model": "registration.bcgreenhousegasid",
    "fields": {
      "id": "23219999999",
      "issued_at": "2023-10-13T15:27:00.000Z",
      "comments": "For Operation 6"
    }
  },
  {
    "model": "registration.bcgreenhousegasid",
    "fields": {
      "id": "23219990006",
      "issued_at": "2023-10-13T15:27:00.000Z",
      "comments": "For Operation 7"
    }
  },
  {
    "model": "registration.bcgreenhousegasid",
    "fields": {
      "id": "23219990007",
      "issued_at": "2023-10-13T15:27:00.000Z",
      "comments": "For Operation 8"
    }
  },
  {
    "model": "registration.bcgreenhousegasid",
    "fields": {
      "id": "23219990008",
      "issued_at": "2023-10-13T15:27:00.000Z",
      "comments": "For Operation 9"
    }
  },
  {
    "model": "registration.bcgreenhousegasid",
    "fields": {
      "id": "23219990009",
      "issued_at": "2023-10-13T15:27:00.000Z",
      "comments": "For Operation 10"
    }
  },
  {
    "model": "registration.bcgreenhousegasid",
    "fields": {
      "id": "23219990010",
      "issued_at": "2023-10-13T15:27:00.000Z",
      "comments": "For Operation 11"
    }
  },
  {
    "model": "registration.bcgreenhousegasid",
    "fields": {
      "id": "23219990011",
      "issued_at": "2023-10-13T15:27:00.000Z",
      "comments": "For Operation 12"
    }
  },
  {
    "model": "registration.bcgreenhousegasid",
    "fields": {
      "id": "23219990012",
      "issued_at": "2023-10-13T15:27:00.000Z",
      "comments": "For Operation 13"
    }
  },
  {
    "model": "registration.bcgreenhousegasid",
    "fields": {
      "id": "23219990013",
      "issued_at": "2023-10-13T15:27:00.000Z",
      "comments": "For Operation 14"
    }
  },
  {
    "model": "registration.bcgreenhousegasid",
    "fields": {
      "id": "23219990014",
      "issued_at": "2023-10-13T15:27:00.000Z",
      "comments": "For Operation 15"
    }
  },
  {
    "model": "registration.bcgreenhousegasid",
    "fields": {
      "id": "23219990015",
      "issued_at": "2023-10-13T15:27:00.000Z",
      "comments": "For Operation 16"
    }
  },
  {
    "model": "registration.bcgreenhousegasid",
    "fields": {
      "id": "23219990016",
      "issued_at": "2023-10-13T15:27:00.000Z",
      "comments": "For Operation 17"
    }
  },
  {
    "model": "registration.bcgreenhousegasid",
    "fields": {
      "id": "23219990017",
      "issued_at": "2023-10-13T15:27:00.000Z",
      "comments": "For Operation 18"
    }
  },
  {
    "model": "registration.bcgreenhousegasid",
    "fields": {
      "id": "23219990018",
      "issued_at": "2023-10-13T15:27:00.000Z",
      "comments": "For Operation 19"
    }
  },
  {
    "model": "registration.bcgreenhousegasid",
    "fields": {
      "id": "23219990019",
      "issued_at": "2023-10-13T15:27:00.000Z",
      "comments": "For Operation 20"
    }
  },
  {
    "model": "registration.bcgreenhousegasid",
    "fields": {
      "id": "23219990020",
      "issued_at": "2023-10-13T15:27:00.000Z",
      "comments": "For Operation 21"
    }
  },
  {
    "model": "registration.bcgreenhousegasid",
    "fields": {
      "id": "23219990021",
      "issued_at": "2023-10-13T15:27:00.000Z",
      "comments": "For Operation 22"
    }
  },
  {
    "model": "registration.bcgreenhousegasid",
    "fields": {
      "id": "23219990022",
      "issued_at": "2023-10-13T15:27:00.000Z",
      "comments": "For Operation 23"
    }
  },
  {
    "model": "registration.bcgreenhousegasid",
    "fields": {
      "id": "23219990023",
      "issued_at": "2023-10-13T15:27:00.000Z",
      "comments": "For Operation 24"
    }
  },
  {
    "model": "registration.bcgreenhousegasid",
    "fields": {
      "id": "13219990006",
      "issued_at": "2024-10-31T15:27:00.000Z"
    }
  },
  {
    "model": "registration.bcgreenhousegasid",
    "fields": {
      "id": "13219990007",
      "issued_at": "2024-10-31T15:27:00.000Z"
    }
  },
  {
    "model": "registration.bcgreenhousegasid",
    "fields": {
      "id": "13219990008",
      "issued_at": "2024-10-31T15:27:00.000Z"
    }
  },
  {
    "model": "registration.bcgreenhousegasid",
    "fields": {
      "id": "13219990009",
      "issued_at": "2024-10-31T15:27:00.000Z"
    }
  },
  {
    "model": "registration.bcgreenhousegasid",
    "fields": {
      "id": "13219990010",
      "issued_at": "2024-10-31T15:27:00.000Z"
    }
  },
  {
    "model": "registration.bcgreenhousegasid",
    "fields": {
      "id": "13219990011",
      "issued_at": "2024-10-31T15:27:00.000Z"
    }
  },
  {
    "model": "registration.bcgreenhousegasid",
    "fields": {
      "id": "13219990012",
      "issued_at": "2024-10-31T15:27:00.000Z"
    }
  },
  {
    "model": "registration.bcgreenhousegasid",
    "fields": {
      "id": "13219990013",
      "issued_at": "2024-10-31T15:27:00.000Z"
    }
  },
  {
    "model": "registration.bcgreenhousegasid",
    "fields": {
      "id": "13219990014",
      "issued_at": "2024-10-31T15:27:00.000Z"
    }
  },
  {
    "model": "registration.bcgreenhousegasid",
    "fields": {
      "id": "13219990015",
      "issued_at": "2024-10-31T15:27:00.000Z"
    }
  },
  {
    "model": "registration.bcgreenhousegasid",
    "fields": {
      "id": "13219990016",
      "issued_at": "2024-10-31T15:27:00.000Z"
    }
  },
  {
    "model": "registration.bcgreenhousegasid",
    "fields": {
      "id": "13219990017",
      "issued_at": "2024-10-31T15:27:00.000Z"
    }
  },
  {
    "model": "registration.bcgreenhousegasid",
    "fields": {
      "id": "13219990018",
      "issued_at": "2024-10-31T15:27:00.000Z"
    }
  },
  {
    "model": "registration.bcgreenhousegasid",
    "fields": {
      "id": "13219990019",
      "issued_at": "2024-10-31T15:27:00.000Z"
    }
  },
  {
    "model": "registration.bcgreenhousegasid",
    "fields": {
      "id": "13219990020",
      "issued_at": "2024-10-31T15:27:00.000Z"
    }
  },
  {
    "model": "registration.bcgreenhousegasid",
    "fields": {
      "id": "13219990021",
      "issued_at": "2024-10-31T15:27:00.000Z"
    }
  },
  {
    "model": "registration.bcgreenhousegasid",
    "fields": {
      "id": "13219990022",
      "issued_at": "2024-10-31T15:27:00.000Z"
    }
  },
  {
    "model": "registration.bcgreenhousegasid",
    "fields": {
      "id": "13219990023",
      "issued_at": "2024-10-31T15:27:00.000Z"
    }
  },
  {
    "model": "registration.bcgreenhousegasid",
    "fields": {
      "id": "13219990024",
      "issued_at": "2024-10-31T15:27:00.000Z"
    }
  },
  {
    "model": "registration.bcgreenhousegasid",
    "fields": {
      "id": "13219990025",
      "issued_at": "2024-10-31T15:27:00.000Z"
    }
  },
  {
    "model": "registration.bcgreenhousegasid",
    "fields": {
      "id": "13219990026",
      "issued_at": "2024-10-31T15:27:00.000Z"
    }
  },
  {
    "model": "registration.bcgreenhousegasid",
    "fields": {
      "id": "13219990027",
      "issued_at": "2024-10-31T15:27:00.000Z"
    }
  },
  {
    "model": "registration.bcgreenhousegasid",
    "fields": {
      "id": "13219990999",
      "issued_at": "2024-10-31T15:27:00.000Z"
    }
  },
  {
    "model": "registration.bcgreenhousegasid",
    "fields": {
      "id": "13219990028",
      "issued_at": "2024-10-31T15:27:00.000Z"
    }
  },
  {
    "model": "registration.bcgreenhousegasid",
    "fields": {
      "id": "13219990029",
      "issued_at": "2024-10-31T15:27:00.000Z"
    }
  },
  {
    "model": "registration.bcgreenhousegasid",
    "fields": {
      "id": "13219990030",
      "issued_at": "2024-10-31T15:27:00.000Z"
    }
  },
  {
    "model": "registration.bcgreenhousegasid",
    "fields": {
      "id": "13219990031",
      "issued_at": "2024-10-31T15:27:00.000Z"
    }
  },
  {
    "model": "registration.bcgreenhousegasid",
    "fields": {
      "id": "13219990032",
      "issued_at": "2024-10-31T15:27:00.000Z"
    }
  },
  {
    "model": "registration.bcgreenhousegasid",
    "fields": {
      "id": "13219990033",
      "issued_at": "2024-10-31T15:27:00.000Z"
    }
  },
  {
    "model": "registration.bcgreenhousegasid",
    "fields": {
      "id": "13219990034",
      "issued_at": "2024-10-31T15:27:00.000Z"
    }
  },
  {
    "model": "registration.bcgreenhousegasid",
    "fields": {
      "id": "13219990035",
      "issued_at": "2024-10-31T15:27:00.000Z"
    }
  },
  {
    "model": "registration.bcgreenhousegasid",
    "fields": {
      "id": "13219990036",
      "issued_at": "2024-10-31T15:27:00.000Z"
    }
  },
  {
    "model": "registration.bcgreenhousegasid",
    "fields": {
      "id": "13219990037",
      "issued_at": "2024-10-31T15:27:00.000Z"
    }
  },
  {
    "model": "registration.bcgreenhousegasid",
    "fields": {
      "id": "13219990038",
      "issued_at": "2024-10-31T15:27:00.000Z"
    }
  },
  {
    "model": "registration.bcgreenhousegasid",
    "fields": {
      "id": "13219990039",
      "issued_at": "2024-10-31T15:27:00.000Z"
    }
  },
  {
    "model": "registration.bcgreenhousegasid",
    "fields": {
      "id": "13219990040",
      "issued_at": "2024-10-31T15:27:00.000Z"
    }
  },
  {
    "model": "registration.bcgreenhousegasid",
    "fields": {
      "id": "13219990041",
      "issued_at": "2024-10-31T15:27:00.000Z"
    }
  },
  {
    "model": "registration.bcgreenhousegasid",
    "fields": {
      "id": "13219990042",
      "issued_at": "2024-10-31T15:27:00.000Z"
    }
  },
  {
    "model": "registration.bcgreenhousegasid",
    "fields": {
      "id": "13219990043",
      "issued_at": "2024-10-31T15:27:00.000Z"
    }
  },
  {
    "model": "registration.bcgreenhousegasid",
    "fields": {
      "id": "13219990044",
      "issued_at": "2024-10-31T15:27:00.000Z"
    }
  },
  {
    "model": "registration.bcgreenhousegasid",
    "fields": {
      "id": "13219990045",
      "issued_at": "2024-10-31T15:27:00.000Z"
    }
  },
  {
    "model": "registration.bcgreenhousegasid",
    "fields": {
      "id": "13219990046",
      "issued_at": "2024-10-31T15:27:00.000Z"
    }
  }
]
