[
  {
    "title": "Users",
    "content": "For managing internal Clean Growth users.",
    "links": [{ "title": "Users ➤", "href": "/dashboard/users" }]
  },
  {
    "title": "Operators",
    "content": "For managing external operator admin access requests.",
    "links": [{ "title": "Operators ➤", "href": "/dashboard/operators" }]
  },
  {
    "title": "Operations",
    "content": "For managing applications for a B.C. OBPS Regulated Operation ID.",
    "links": [{ "title": "Operations ➤", "href": "/dashboard/operations" }]
  },
  {
    "title": "Report a Problem",
    "content": "Something wrong? Report a problem to the team",
    "links": [{ "title": "Tell the team ➤", "href": "/dashboard/problem" }]
  }
]
